earth_age_calculator-0.2.1.dist-info/METADATA
earth_age_calculator-0.2.1.dist-info/WHEEL
earth_age_calculator/__init__.py
earth_age_calculator/earth.py
earth_age_calculator-0.2.1.dist-info/RECORD
