Metadata-Version: 2.1
Name: earth-age-calculator
Version: 0.2.1
Summary: I'll calculate the age of the earth.
Author-Email: dmario24 <data.mario24@gmail.com>
License: MIT
Requires-Python: >=3.9
